hyperalignment/__init__.py
hyperalignment/ensemble.py
hyperalignment/linalg.py
hyperalignment/local_template.py
hyperalignment/procrustes.py
hyperalignment/ridge.py
hyperalignment/searchlight.py
hyperalignment/sparse.py
hyperalignment-0.1.1.data/scripts/npls
hyperalignment-0.1.1.data/scripts/rmdirs
hyperalignment-0.1.1.dist-info/METADATA
hyperalignment-0.1.1.dist-info/WHEEL
hyperalignment-0.1.1.dist-info/top_level.txt
hyperalignment-0.1.1.dist-info/RECORD
