Metadata-Version: 2.1
Name: hyperalignment
Version: 0.1.1
Summary: Hyperalignment algorithms for functional alignment of fMRI data.
Home-page: https://feilong.github.io/hyperalignment/
Author: Ma Feilong
Author-email: mafeilong@gmail.com
Project-URL: Bug Tracker, https://github.com/feilong/hyperalignment/issues
Project-URL: Source Code, https://github.com/feilong/hyperalignment
Keywords: hyperalignment,mvpa,brain,fmri,neuroscience,neuroimaging
Classifier: Programming Language :: Python :: 3 :: Only
Classifier: Programming Language :: Python :: 3.6
Classifier: Programming Language :: Python :: 3.7
Classifier: Programming Language :: Python :: 3.8
Classifier: Programming Language :: Python :: 3.9
Classifier: Programming Language :: Python :: 3.10
Requires-Python: >=3.6
Requires-Dist: numpy
Requires-Dist: scipy
Requires-Dist: scikit-learn
Provides-Extra: tests
Requires-Dist: pytest ; extra == 'tests'
